structmanager/__init__.py
structmanager/nastranmodel.py
structmanager/optmodel.py
structmanager/sas.py
structmanager/setup.py
structmanager/structmodel.py
structmanager/version.py
structmanager/excel/__init__.py
structmanager/excel/excel.py
structmanager/outreader/__init__.py
structmanager/outreader/forces1d.py
structmanager/outreader/forces2d.py
structmanager/outreader/hdf5_reader.py
structmanager/structelem/__init__.py
structmanager/structelem/base.py
structmanager/structelem/flanges.py
structmanager/structelem/panel.py
structmanager/structelem/panelcomp.py
structmanager/structelem/shearclip.py
structmanager/structelem/stringer.py
structmanager/structelem/web.py
structmanager-0.4.0.data/data/LICENSE
structmanager-0.4.0.data/data/README.rst
structmanager-0.4.0.data/data/version.py
structmanager-0.4.0.dist-info/METADATA
structmanager-0.4.0.dist-info/RECORD
structmanager-0.4.0.dist-info/WHEEL
structmanager-0.4.0.dist-info/top_level.txt
