Metadata-Version: 2.1
Name: structmanager
Version: 0.4.0
Summary: Structural Analysis Helper
Home-page: https://github.com/compmech/structmanager
Author: Saullo G. P. Castro
Author-email: castrosaullo@gmail.com
License: BSD
Keywords: structural analysis; stress analysis; automation
Platform: UNKNOWN
Classifier: Development Status :: 3 - Alpha
Classifier: Intended Audience :: Science/Research
Classifier: Intended Audience :: Developers
Classifier: Intended Audience :: Education
Classifier: Topic :: Scientific/Engineering :: Mathematics
Classifier: License :: OSI Approved :: BSD License
Classifier: Operating System :: Microsoft :: Windows
Classifier: Programming Language :: Python :: 2.7
Classifier: Programming Language :: Python :: 3.5
Classifier: Operating System :: Unix
Requires-Dist: numpy
Requires-Dist: scipy
Requires-Dist: coveralls
Requires-Dist: pyNastran
Requires-Dist: setuptools-git-version
